docs/source/conf.py
plantbrain_fastml/__init__.py
plantbrain_fastml/base/__init__.py
plantbrain_fastml/base/base_classifier.py
plantbrain_fastml/base/base_forecaster.py
plantbrain_fastml/base/base_preprocessor.py
plantbrain_fastml/base/base_regressor.py
plantbrain_fastml/base/model_manager_mixin.py
plantbrain_fastml/config/__init__.py
plantbrain_fastml/config/deafults.py
plantbrain_fastml/managers/__init__.py
plantbrain_fastml/managers/classifier_manager.py
plantbrain_fastml/managers/forecaster_manager.py
plantbrain_fastml/managers/regressor_manager.py
plantbrain_fastml/models/__init__.py
plantbrain_fastml/models/classifiers/__init__.py
plantbrain_fastml/models/classifiers/logistic_regression.py
plantbrain_fastml/models/classifiers/random_forest_classifier.py
plantbrain_fastml/models/classifiers/svc.py
plantbrain_fastml/models/forecasters/__init__.py
plantbrain_fastml/models/forecasters/linear_regression.py
plantbrain_fastml/models/regressors/GradientBoostingRegression.py
plantbrain_fastml/models/regressors/KNN_regression.py
plantbrain_fastml/models/regressors/SVRegression.py
plantbrain_fastml/models/regressors/__init__.py
plantbrain_fastml/models/regressors/adaboost.py
plantbrain_fastml/models/regressors/bayesian_ridge.py
plantbrain_fastml/models/regressors/decesion_tree.py
plantbrain_fastml/models/regressors/elastic_net.py
plantbrain_fastml/models/regressors/lasso.py
plantbrain_fastml/models/regressors/linear_regression.py
plantbrain_fastml/models/regressors/random_forest.py
plantbrain_fastml/models/regressors/ridge.py
plantbrain_fastml/utils/__init__.py
plantbrain_fastml/utils/helpers.py
plantbrain_fastml/utils/metrics.py
plantbrain_fastml/utils/preprocessing.py
plantbrain_fastml/utils/processWrapper.py
plantbrain_fastml-0.4.5.dist-info/licenses/LICENSE
tests/test1.py
plantbrain_fastml-0.4.5.dist-info/METADATA
plantbrain_fastml-0.4.5.dist-info/WHEEL
plantbrain_fastml-0.4.5.dist-info/top_level.txt
plantbrain_fastml-0.4.5.dist-info/RECORD
