Metadata-Version: 2.4
Name: plantbrain-fastml
Version: 0.4.5
Summary: An AutoML package by plantBrain with classification, regression, and forecasting support.
Home-page: https://github.com/ALGO8AI/plantbrain-fastml.git
Author: Himanshu Bhansali, Himanshu Ranjan
Author-email: Himanshu Bhansali <himanshu.bhansali@algo8.ai>, Himanshu Ranjan <Himanshu.ranjan@algo8.ai>
License: MIT
Project-URL: Documentation, https://github.com/ALGO8AI/plantbrain-fastml.git
Project-URL: Source, https://github.com/ALGO8AI/plantbrain-fastml.git
Keywords: AutoML,classification,regression,forecasting,machine learning
Classifier: Programming Language :: Python :: 3
Classifier: License :: OSI Approved :: MIT License
Classifier: Operating System :: OS Independent
Classifier: Intended Audience :: Developers
Classifier: Topic :: Scientific/Engineering :: Artificial Intelligence
Classifier: Topic :: Software Development :: Libraries :: Python Modules
Requires-Python: >=3.11.0
License-File: LICENSE
Requires-Dist: scikit-learn>=1.6.1
Requires-Dist: pandas>=2.2.3
Requires-Dist: numpy>=2.1.3
Requires-Dist: optuna>=4.1.0
Requires-Dist: matplotlib>=3.10.0
Dynamic: author
Dynamic: home-page
Dynamic: license-file
Dynamic: requires-python
